linc/__init__.py
linc/detector/__init__.py
linc/detector/helper/__init__.py
linc/detector/helper/coco_eval.py
linc/detector/helper/coco_utils.py
linc/detector/helper/engine.py
linc/detector/helper/group_by_aspect_ratio.py
linc/detector/helper/transforms.py
linc/detector/helper/utils.py
linc/detector/models/__init__.py
linc/detector/models/_utils.py
linc/detector/models/resnet.py
linc/detector/models/utils.py
linc/detector/models/detection/__init__.py
linc/detector/models/detection/_utils.py
linc/detector/models/detection/backbone_utils.py
linc/detector/models/detection/custom_nms.py
linc/detector/models/detection/faster_rcnn.py
linc/detector/models/detection/generalized_rcnn.py
linc/detector/models/detection/image_list.py
linc/detector/models/detection/roi_heads.py
linc/detector/models/detection/rpn.py
linc/detector/models/detection/transform.py
linc_detector-0.1.3.dist-info/LICENSE
linc_detector-0.1.3.dist-info/METADATA
linc_detector-0.1.3.dist-info/WHEEL
linc_detector-0.1.3.dist-info/top_level.txt
linc_detector-0.1.3.dist-info/RECORD
