Metadata-Version: 2.1
Name: linc-detector
Version: 0.1.3
Summary: Python package that holds model to detect lion facial parts
Author: Lion Guardians
Author-email: tech@linclion.org
Classifier: Topic :: Software Development :: Libraries
Classifier: Intended Audience :: Developers
Classifier: Programming Language :: Python :: 3.7
Classifier: Programming Language :: Python :: 3.8
License-File: LICENSE
Requires-Dist: numpy (==1.23.3)
Requires-Dist: future (==0.16.0)
Requires-Dist: torch (==1.10.1)
Requires-Dist: torchvision (==0.11.2)
